denseclus/DenseClus.py
denseclus/__init__.py
denseclus/__version__.py
denseclus/categorical.py
denseclus/numerical.py
denseclus/utils.py
amazon_denseclus-0.2.2.dist-info/METADATA
amazon_denseclus-0.2.2.dist-info/WHEEL
amazon_denseclus-0.2.2.dist-info/top_level.txt
amazon_denseclus-0.2.2.dist-info/RECORD
