Metadata-Version: 2.1
Name: amazon_denseclus
Version: 0.2.2
Summary: Dense Clustering for Mixed Data Types
Home-page: https://github.com/awslabs/amazon-denseclus
Author: Charles Frenzel & Baichuan Sun
Project-URL: Bug Tracker, https://github.com/awslabs/amazon-denseclus/issues
Project-URL: Documentation, https://github.com/awslabs/amazon-denseclus/notebooks
Project-URL: Source Code, https://github.com/awslabs/amazon-denseclus
Keywords: amazon dense clustering
Platform: any
Classifier: Programming Language :: Python :: 3
Classifier: License :: OSI Approved :: MIT License
Classifier: Operating System :: OS Independent
Classifier: Topic :: Software Development :: Libraries :: Python Modules
Classifier: Development Status :: 3 - Alpha
Classifier: Programming Language :: Python :: 3.10
Requires-Python: >=3.10, <3.12
Requires-Dist: umap-learn >=0.5.1
Requires-Dist: numpy >=1.20.2
Requires-Dist: hdbscan >=0.8.27
Requires-Dist: numba >=0.51.2
Requires-Dist: pandas >=1.2.4
Requires-Dist: scikit-learn >=0.24.2
Requires-Dist: seaborn >=0.13.0
Provides-Extra: gpu-cu11
Requires-Dist: cuml-cu11 ; extra == 'gpu-cu11'
Provides-Extra: gpu-cu12
Requires-Dist: cuml-cu12 ; extra == 'gpu-cu12'
Provides-Extra: test
Requires-Dist: pytest ; extra == 'test'
Requires-Dist: pytest-cov ; extra == 'test'
